{"nodes": [{"isOutput": true, "isInput": false, "activation": "sigmoid", "bias": -0.4390299222961398}, {"isOutput": true, "isInput": false, "activation": "sigmoid", "bias": -0.8336946738306898}, {"isOutput": true, "isInput": false, "activation": "sigmoid", "bias": -0.3186320568543508}, {"isOutput": false, "isInput": false, "activation": "linear", "bias": 0.20894760795168432}, {"isOutput": false, "isInput": true, "activation": "linear", "bias": 0.8304697833593466}, {"isOutput": false, "isInput": true, "activation": "linear", "bias": -0.5029475904469702}, {"isOutput": false, "isInput": true, "activation": "linear", "bias": -0.580747527049462}, {"isOutput": false, "isInput": true, "activation": "linear", "bias": 0.7774212494578028}, {"isOutput": false, "isInput": true, "activation": "linear", "bias": 0.8980232614608092}, {"isOutput": false, "isInput": true, "activation": "linear", "bias": 0.8342939551439137}, {"isOutput": false, "isInput": true, "activation": "linear", "bias": -0.17210204694973763}, {"isOutput": false, "isInput": true, "activation": "linear", "bias": 0.05171961715791573}, {"isOutput": false, "isInput": true, "activation": "linear", "bias": -0.5890713744888396}, {"isOutput": false, "isInput": true, "activation": "linear", "bias": 0.3854855381296405}, {"isOutput": false, "isInput": true, "activation": "linear", "bias": 0.9705114967307258}, {"isOutput": false, "isInput": true, "activation": "linear", "bias": 0.9123212849645899}, {"isOutput": false, "isInput": true, "activation": "linear", "bias": -0.0733172051901152}, {"isOutput": false, "isInput": true, "activation": "linear", "bias": -0.8979209447620222}, {"isOutput": false, "isInput": true, "activation": "linear", "bias": 0.5824214054630912}, {"isOutput": false, "isInput": true, "activation": "linear", "bias": 0.15955664542937487}, {"isOutput": false, "isInput": true, "activation": "linear", "bias": -0.4383493164525252}, {"isOutput": false, "isInput": true, "activation": "linear", "bias": -0.24252567018593485}, {"isOutput": false, "isInput": true, "activation": "linear", "bias": -0.8248976490363547}, {"isOutput": false, "isInput": true, "activation": "linear", "bias": -0.11029052230922654}, {"isOutput": false, "isInput": true, "activation": "linear", "bias": 0.0911428617617771}, {"isOutput": false, "isInput": true, "activation": "linear", "bias": -0.35882225042696936}, {"isOutput": false, "isInput": true, "activation": "linear", "bias": -0.3805106141957544}, {"isOutput": false, "isInput": true, "activation": "linear", "bias": -0.12325044990509992}, {"isOutput": false, "isInput": true, "activation": "linear", "bias": -0.9394990886810024}, {"isOutput": false, "isInput": true, "activation": "linear", "bias": 0.9859257878940466}, {"isOutput": false, "isInput": true, "activation": "linear", "bias": 0.48157494143996726}, {"isOutput": false, "isInput": true, "activation": "linear", "bias": -0.8471423278221999}, {"isOutput": false, "isInput": true, "activation": "linear", "bias": -0.08292337235602631}, {"isOutput": false, "isInput": true, "activation": "linear", "bias": -0.8293395296980843}, {"isOutput": false, "isInput": true, "activation": "linear", "bias": 0.11079419369269461}, {"isOutput": false, "isInput": true, "activation": "linear", "bias": 0.24414734808818395}, {"isOutput": false, "isInput": true, "activation": "linear", "bias": -0.9155418133123852}, {"isOutput": false, "isInput": true, "activation": "linear", "bias": 0.6445668170333565}, {"isOutput": false, "isInput": true, "activation": "linear", "bias": 0.3189304310943204}, {"isOutput": false, "isInput": true, "activation": "linear", "bias": 0.6669647548597339}, {"isOutput": false, "isInput": true, "activation": "linear", "bias": -0.6172476776949176}, {"isOutput": false, "isInput": true, "activation": "linear", "bias": -0.7509715509284594}, {"isOutput": false, "isInput": true, "activation": "linear", "bias": 0.8444212487274023}, {"isOutput": false, "isInput": true, "activation": "linear", "bias": 0.6846402372292244}, {"isOutput": false, "isInput": true, "activation": "linear", "bias": 0.4816542565743809}, {"isOutput": false, "isInput": true, "activation": "linear", "bias": -0.6898382589923064}, {"isOutput": false, "isInput": true, "activation": "linear", "bias": 0.6400951379604563}, {"isOutput": false, "isInput": true, "activation": "linear", "bias": -0.10343390867861291}, {"isOutput": false, "isInput": true, "activation": "linear", "bias": 0.36062742004759274}, {"isOutput": false, "isInput": true, "activation": "linear", "bias": -0.026012191949785546}, {"isOutput": false, "isInput": true, "activation": "linear", "bias": 0.854703181002286}, {"isOutput": false, "isInput": true, "activation": "linear", "bias": -0.9746231874528302}, {"isOutput": false, "isInput": true, "activation": "linear", "bias": -0.13549393852027092}, {"isOutput": false, "isInput": true, "activation": "linear", "bias": 0.5667025733264837}, {"isOutput": false, "isInput": true, "activation": "linear", "bias": 0.2038272752321535}, {"isOutput": false, "isInput": true, "activation": "linear", "bias": 0.7189881218321457}, {"isOutput": false, "isInput": true, "activation": "linear", "bias": -0.3661950484000114}, {"isOutput": false, "isInput": true, "activation": "linear", "bias": -0.5959451748089071}, {"isOutput": false, "isInput": true, "activation": "linear", "bias": 0.7099068961475392}, {"isOutput": false, "isInput": true, "activation": "linear", "bias": -0.7201936096834236}, {"isOutput": false, "isInput": true, "activation": "linear", "bias": -0.25306833974419796}, {"isOutput": false, "isInput": true, "activation": "linear", "bias": -0.9265429373455862}, {"isOutput": false, "isInput": true, "activation": "linear", "bias": -0.858358985239184}, {"isOutput": false, "isInput": true, "activation": "linear", "bias": 0.2217337586600876}, {"isOutput": false, "isInput": true, "activation": "linear", "bias": -0.8757450605280386}, {"isOutput": false, "isInput": true, "activation": "linear", "bias": -0.4192098089265226}, {"isOutput": false, "isInput": true, "activation": "linear", "bias": -0.44215366207134776}, {"isOutput": false, "isInput": true, "activation": "linear", "bias": 0.8226523204578289}, {"isOutput": false, "isInput": true, "activation": "linear", "bias": -0.017942278620484142}, {"isOutput": false, "isInput": true, "activation": "linear", "bias": 0.8909709028288253}, {"isOutput": false, "isInput": true, "activation": "linear", "bias": -0.5111633306571821}, {"isOutput": false, "isInput": true, "activation": "linear", "bias": 0.050008739344275854}, {"isOutput": false, "isInput": true, "activation": "linear", "bias": 0.8728172323046037}, {"isOutput": false, "isInput": true, "activation": "linear", "bias": -0.06313055093122433}, {"isOutput": false, "isInput": true, "activation": "linear", "bias": -0.649965975220002}, {"isOutput": false, "isInput": true, "activation": "linear", "bias": -0.7451174362359567}, {"isOutput": false, "isInput": true, "activation": "linear", "bias": -0.7350264889554374}, {"isOutput": false, "isInput": true, "activation": "linear", "bias": -0.0434620719444212}, {"isOutput": false, "isInput": true, "activation": "linear", "bias": -0.4761627894987124}, {"isOutput": false, "isInput": true, "activation": "linear", "bias": -0.670758564647723}, {"isOutput": false, "isInput": true, "activation": "linear", "bias": 0.24013839492586042}, {"isOutput": false, "isInput": true, "activation": "linear", "bias": -0.5877489204902406}, {"isOutput": false, "isInput": true, "activation": "linear", "bias": -0.4326394417349293}, {"isOutput": false, "isInput": true, "activation": "linear", "bias": 0.05711627397798846}, {"isOutput": false, "isInput": true, "activation": "linear", "bias": -0.5026503518840282}, {"isOutput": false, "isInput": true, "activation": "linear", "bias": -0.15066903453539915}, {"isOutput": false, "isInput": true, "activation": "linear", "bias": -0.18213546289613292}, {"isOutput": false, "isInput": true, "activation": "linear", "bias": -0.33772405708479236}, {"isOutput": false, "isInput": true, "activation": "linear", "bias": 0.8751989131692208}, {"isOutput": false, "isInput": true, "activation": "linear", "bias": 0.7577264417576006}, {"isOutput": false, "isInput": true, "activation": "linear", "bias": -0.4462939587356416}, {"isOutput": false, "isInput": true, "activation": "linear", "bias": -0.7305647117308902}, {"isOutput": false, "isInput": true, "activation": "linear", "bias": -0.9437241064539037}, {"isOutput": false, "isInput": true, "activation": "linear", "bias": -0.9676419585398}, {"isOutput": false, "isInput": true, "activation": "linear", "bias": -0.44119534471525257}, {"isOutput": false, "isInput": true, "activation": "linear", "bias": -0.3463503514501154}, {"isOutput": false, "isInput": true, "activation": "linear", "bias": 0.0515778386352832}, {"isOutput": false, "isInput": true, "activation": "linear", "bias": 0.2841224881063942}, {"isOutput": false, "isInput": true, "activation": "linear", "bias": 0.5376315483317646}, {"isOutput": false, "isInput": true, "activation": "linear", "bias": -0.6761494172269007}, {"isOutput": false, "isInput": true, "activation": "linear", "bias": 0.6863388766163561}, {"isOutput": false, "isInput": true, "activation": "linear", "bias": -0.6344006668530031}, {"isOutput": false, "isInput": true, "activation": "linear", "bias": -0.11634407838172578}, {"isOutput": false, "isInput": true, "activation": "linear", "bias": -0.7735395223440722}, {"isOutput": false, "isInput": true, "activation": "linear", "bias": 0.23254539918914507}, {"isOutput": false, "isInput": true, "activation": "linear", "bias": 0.5479804159504658}, {"isOutput": false, "isInput": true, "activation": "linear", "bias": 0.863243048155601}, {"isOutput": false, "isInput": true, "activation": "linear", "bias": -0.965125347987851}, {"isOutput": false, "isInput": true, "activation": "linear", "bias": 0.4669100457566504}, {"isOutput": false, "isInput": true, "activation": "linear", "bias": 0.4592500488357316}, {"isOutput": false, "isInput": true, "activation": "linear", "bias": -0.11752295708163363}, {"isOutput": false, "isInput": true, "activation": "linear", "bias": 0.8320889511543004}, {"isOutput": false, "isInput": true, "activation": "linear", "bias": -0.07958210657023335}, {"isOutput": false, "isInput": true, "activation": "linear", "bias": 0.9995289890003467}, {"isOutput": false, "isInput": true, "activation": "linear", "bias": 0.8534700605908634}, {"isOutput": false, "isInput": true, "activation": "linear", "bias": 0.4092087869968477}, {"isOutput": false, "isInput": true, "activation": "linear", "bias": 0.3003399715393422}, {"isOutput": false, "isInput": true, "activation": "linear", "bias": 0.8731361301669263}, {"isOutput": false, "isInput": true, "activation": "linear", "bias": 0.6416516524224942}, {"isOutput": false, "isInput": true, "activation": "linear", "bias": -0.5058051256404379}, {"isOutput": false, "isInput": true, "activation": "linear", "bias": 0.7016113767493157}, {"isOutput": false, "isInput": true, "activation": "linear", "bias": -0.991748547346573}, {"isOutput": false, "isInput": true, "activation": "linear", "bias": -0.6915532293840259}, {"isOutput": false, "isInput": true, "activation": "linear", "bias": -0.5628183262926796}, {"isOutput": false, "isInput": true, "activation": "linear", "bias": 0.7689316914642286}, {"isOutput": false, "isInput": true, "activation": "linear", "bias": -0.08232245781034231}, {"isOutput": false, "isInput": true, "activation": "linear", "bias": -0.14854467758130263}, {"isOutput": false, "isInput": true, "activation": "linear", "bias": 0.1404998632077532}, {"isOutput": false, "isInput": true, "activation": "linear", "bias": -0.8787412236751373}, {"isOutput": false, "isInput": true, "activation": "linear", "bias": -0.13277439332231}, {"isOutput": false, "isInput": true, "activation": "linear", "bias": 0.43858141226444625}, {"isOutput": false, "isInput": true, "activation": "linear", "bias": 0.17151184702415367}, {"isOutput": false, "isInput": true, "activation": "linear", "bias": -0.6159599747399676}, {"isOutput": false, "isInput": true, "activation": "linear", "bias": -0.9710608057558443}, {"isOutput": false, "isInput": true, "activation": "linear", "bias": -0.10056591887295108}, {"isOutput": false, "isInput": true, "activation": "linear", "bias": 0.7348994916441776}, {"isOutput": false, "isInput": true, "activation": "linear", "bias": 0.10370467788387394}, {"isOutput": false, "isInput": true, "activation": "linear", "bias": -0.989540668017237}, {"isOutput": false, "isInput": true, "activation": "linear", "bias": 0.046882338857017425}, {"isOutput": false, "isInput": true, "activation": "linear", "bias": -0.8379274680658286}, {"isOutput": false, "isInput": true, "activation": "linear", "bias": -0.0849927638650867}, {"isOutput": false, "isInput": true, "activation": "linear", "bias": 0.2505470961138059}, {"isOutput": false, "isInput": true, "activation": "linear", "bias": 0.28490133265054673}, {"isOutput": false, "isInput": true, "activation": "linear", "bias": 0.27269062028726676}, {"isOutput": false, "isInput": true, "activation": "linear", "bias": 0.3238742898209832}, {"isOutput": false, "isInput": true, "activation": "linear", "bias": -0.5430578490544797}, {"isOutput": false, "isInput": true, "activation": "linear", "bias": 0.7547234121868067}, {"isOutput": false, "isInput": true, "activation": "linear", "bias": -0.2631966652585065}, {"isOutput": false, "isInput": true, "activation": "linear", "bias": 0.42177258477710744}, {"isOutput": false, "isInput": true, "activation": "linear", "bias": -0.22445415054141504}, {"isOutput": false, "isInput": true, "activation": "linear", "bias": -0.5874573258973845}, {"isOutput": false, "isInput": true, "activation": "linear", "bias": -0.21911595993427202}, {"isOutput": false, "isInput": true, "activation": "linear", "bias": 0.7998874076823341}, {"isOutput": false, "isInput": true, "activation": "linear", "bias": -0.6196569603787125}, {"isOutput": false, "isInput": true, "activation": "linear", "bias": 0.7771850414158068}, {"isOutput": false, "isInput": true, "activation": "linear", "bias": -0.131490587276063}], "connections": [{"start": 11, "end": 3, "weight": 0.6953650253686714}, {"start": 3, "end": 1, "weight": -0.47789106910176615}, {"start": 80, "end": 0, "weight": -0.48420221330948987}]}